bluecellulab/__init__.py
bluecellulab/circuit_simulation.py
bluecellulab/connection.py
bluecellulab/dendrogram.py
bluecellulab/exceptions.py
bluecellulab/graph.py
bluecellulab/importer.py
bluecellulab/neuron_interpreter.py
bluecellulab/plotwindow.py
bluecellulab/psection.py
bluecellulab/psegment.py
bluecellulab/rngsettings.py
bluecellulab/tools.py
bluecellulab/type_aliases.py
bluecellulab/utils.py
bluecellulab/verbosity.py
bluecellulab/analysis/__init__.py
bluecellulab/analysis/analysis.py
bluecellulab/analysis/inject_sequence.py
bluecellulab/analysis/plotting.py
bluecellulab/analysis/utils.py
bluecellulab/cell/__init__.py
bluecellulab/cell/cell_dict.py
bluecellulab/cell/core.py
bluecellulab/cell/injector.py
bluecellulab/cell/plotting.py
bluecellulab/cell/random.py
bluecellulab/cell/recording.py
bluecellulab/cell/section_distance.py
bluecellulab/cell/section_tools.py
bluecellulab/cell/serialized_sections.py
bluecellulab/cell/sonata_proxy.py
bluecellulab/cell/stimuli_generator.py
bluecellulab/cell/template.py
bluecellulab/cell/ballstick/__init__.py
bluecellulab/cell/ballstick/emodel.hoc
bluecellulab/cell/ballstick/morphology.asc
bluecellulab/circuit/__init__.py
bluecellulab/circuit/format.py
bluecellulab/circuit/iotools.py
bluecellulab/circuit/node_id.py
bluecellulab/circuit/simulation_access.py
bluecellulab/circuit/synapse_properties.py
bluecellulab/circuit/validate.py
bluecellulab/circuit/circuit_access/__init__.py
bluecellulab/circuit/circuit_access/bluepy_circuit_access.py
bluecellulab/circuit/circuit_access/definition.py
bluecellulab/circuit/circuit_access/sonata_circuit_access.py
bluecellulab/circuit/config/__init__.py
bluecellulab/circuit/config/bluepy_simulation_config.py
bluecellulab/circuit/config/definition.py
bluecellulab/circuit/config/sections.py
bluecellulab/circuit/config/sonata_simulation_config.py
bluecellulab/hoc/Cell.hoc
bluecellulab/hoc/RNGSettings.hoc
bluecellulab/hoc/TDistFunc.hoc
bluecellulab/hoc/TStim.hoc
bluecellulab/hoc/fileUtils.hoc
bluecellulab-2.6.78.dist-info/licenses/AUTHORS.txt
bluecellulab-2.6.78.dist-info/licenses/LICENSE
bluecellulab-2.6.78.dist-info/METADATA
bluecellulab-2.6.78.dist-info/WHEEL
bluecellulab-2.6.78.dist-info/top_level.txt
bluecellulab-2.6.78.dist-info/RECORD
