Metadata-Version: 2.4
Name: bluecellulab
Version: 2.6.78
Summary: Biologically detailed neural network simulations and analysis.
Author: Blue Brain Project, EPFL
License: Apache2.0
Project-URL: Homepage, https://github.com/openbraininstitute/BlueCelluLab
Project-URL: Documentation, https://bluecellulab.readthedocs.io/
Keywords: computational neuroscience,simulation,analysis,SONATA,neural networks,neuron,Blue Brain Project
Classifier: Development Status :: 5 - Production/Stable
Classifier: Environment :: Console
Classifier: License :: OSI Approved :: Apache Software License
Classifier: Operating System :: POSIX
Classifier: Topic :: Scientific/Engineering
Classifier: Programming Language :: Python :: 3
Classifier: Topic :: Utilities
Requires-Python: >=3.10
License-File: LICENSE
License-File: AUTHORS.txt
Requires-Dist: NEURON<9.0.0,>=8.0.2
Requires-Dist: numpy<2.4,>=2.0.0
Requires-Dist: matplotlib<4.0.0,>=3.0.0
Requires-Dist: pandas<3.0.0,>=1.0.0
Requires-Dist: bluepysnap<4.0.0,>=3.0.0
Requires-Dist: pydantic<3.0.0,>=2.5.2
Requires-Dist: typing-extensions>=4.8.0
Requires-Dist: networkx>=3.1
Requires-Dist: h5py>=3.8.0
Requires-Dist: seaborn
Requires-Dist: efel>=5.7.19
Requires-Dist: neo>=0.14.0
Requires-Dist: quantities>=0.16.2
Provides-Extra: examples
Requires-Dist: ipywidgets; extra == "examples"
Dynamic: license-file
